deloscri/__init__.py
deloscri/rmlog.py
deloscri-0.1.0.dist-info/LICENCE.txt
deloscri-0.1.0.dist-info/METADATA
deloscri-0.1.0.dist-info/WHEEL
deloscri-0.1.0.dist-info/entry_points.txt
deloscri-0.1.0.dist-info/top_level.txt
deloscri-0.1.0.dist-info/RECORD
